quorum_fullnode_py/__init__.py
quorum_fullnode_py/exceptions.py
quorum_fullnode_py/api/__init__.py
quorum_fullnode_py/api/base.py
quorum_fullnode_py/api/fullnode.py
quorum_fullnode_py/client/__init__.py
quorum_fullnode_py/client/_http.py
quorum_fullnode_py/client/fullnode.py
quorum_fullnode_py-1.3.2.dist-info/LICENSE
quorum_fullnode_py-1.3.2.dist-info/METADATA
quorum_fullnode_py-1.3.2.dist-info/WHEEL
quorum_fullnode_py-1.3.2.dist-info/top_level.txt
quorum_fullnode_py-1.3.2.dist-info/RECORD
