Metadata-Version: 2.1
Name: quorum-fullnode-py
Version: 1.3.2
Summary: Python SDK for FullNode of QuoRum
Home-page: https://github.com/liujuanjuan1984/quorum_fullnode_py
Author: liujuanjuan1984
Author-email: qiaoanlu@163.com
Project-URL: Github Repo, https://github.com/liujuanjuan1984/quorum_fullnode_py
Project-URL: Bug Tracker, https://github.com/liujuanjuan1984/quorum_fullnode_py/issues
Project-URL: About Quorum, https://github.com/rumsystem/quorum
Keywords: quorum_fullnode_py,rumsystem,quorum
Classifier: Programming Language :: Python :: 3
Classifier: Programming Language :: Python :: 3.7
Classifier: Programming Language :: Python :: 3.8
Classifier: Programming Language :: Python :: 3.9
Classifier: Programming Language :: Python :: 3.10
Classifier: License :: OSI Approved :: MIT License
Classifier: Operating System :: OS Independent
Requires-Python: >=3.7
License-File: LICENSE
Requires-Dist: requests
